lib_pdf_to_img/__init__.py
lib_pdf_to_img/utils.py
pdf_to_img_pdf-0.0.3.dist-info/METADATA
pdf_to_img_pdf-0.0.3.dist-info/WHEEL
pdf_to_img_pdf-0.0.3.dist-info/top_level.txt
pdf_to_img_pdf-0.0.3.dist-info/RECORD
