Metadata-Version: 2.1
Name: pdf_to_img_pdf
Version: 0.0.3
Summary: Converts pdf file to a pdf file where each file is a pdf image
License: BSD
Requires-Dist: fitz ==0.0.1.dev2
Requires-Dist: pynput ==1.7.7
Requires-Dist: setuptools ==69.2.0
